jupyter_tensorboard/__init__.py
jupyter_tensorboard/api_handlers.py
jupyter_tensorboard/application.py
jupyter_tensorboard/handlers.py
jupyter_tensorboard/tensorboard_manager.py
jupyter_tensorboard/static/style.css
jupyter_tensorboard/static/tensorboardlist.js
jupyter_tensorboard/static/tree.js
jupyter_tensorboard-0.1.1.data/scripts/jupyter-tensorboard
jupyter_tensorboard-0.1.1.dist-info/DESCRIPTION.rst
jupyter_tensorboard-0.1.1.dist-info/METADATA
jupyter_tensorboard-0.1.1.dist-info/RECORD
jupyter_tensorboard-0.1.1.dist-info/WHEEL
jupyter_tensorboard-0.1.1.dist-info/entry_points.txt
jupyter_tensorboard-0.1.1.dist-info/metadata.json
jupyter_tensorboard-0.1.1.dist-info/top_level.txt
