Metadata-Version: 2.0
Name: jupyter-tensorboard
Version: 0.1.1
Summary: Start tensorboard in Jupyter! Jupyter notebook integration for tensorboard
Home-page: http://github.com/lspvic/jupyter_tensorboard
Author: lspvic
Author-email: lspvic@qq.com
License: MIT License
Keywords: Jupyter,Notebook,Tensorboard,Tensorflow
Platform: Linux
Platform: Mac OS X
Platform: Windows
Classifier: Intended Audience :: Developers
Classifier: Intended Audience :: Science/Research
Classifier: License :: OSI Approved :: MIT License
Classifier: Programming Language :: Python
Classifier: Programming Language :: Python :: 2.7
Classifier: Programming Language :: Python :: 3
Classifier: Programming Language :: Python :: 3.4
Classifier: Programming Language :: Python :: 3.5
Classifier: Programming Language :: Python :: 3.6
Requires-Dist: notebook (>=5.0)
